{
    "title_ar": "فيلم قصير: رحلة في الجبال",
    "title_en": "Short Film: Mountain Trek",
    "category": "videos",
    "image": "https://images.unsplash.com/photo-1464822759023-fed622ff2c3b?auto=format&fit=crop&q=80&w=800",
    "video_link": "https://vimeo.com/76979871",
    "description_ar": "فيلم سينمائي قصير يوثق رحلة تسلق.",
    "description_en": "Cinematic short film documenting a climbing trip.",
    "body_ar": "استخدام تقنيات تصوير الدرون المتقدمة.",
    "body_en": "Using advanced drone filming techniques.",
    "date": "2024-01-28"
}